odoo9_addon_mrp_bom_location-9.0.1.0.0.99.dev6-py3.8-nspkg.pth
odoo_addons/mrp_bom_location/README.rst
odoo_addons/mrp_bom_location/__init__.py
odoo_addons/mrp_bom_location/__openerp__.py
odoo_addons/mrp_bom_location/i18n/ca.po
odoo_addons/mrp_bom_location/i18n/cs.po
odoo_addons/mrp_bom_location/i18n/da.po
odoo_addons/mrp_bom_location/i18n/de.po
odoo_addons/mrp_bom_location/i18n/en_US.po
odoo_addons/mrp_bom_location/i18n/es.po
odoo_addons/mrp_bom_location/i18n/es_ES.po
odoo_addons/mrp_bom_location/i18n/fi.po
odoo_addons/mrp_bom_location/i18n/fr.po
odoo_addons/mrp_bom_location/i18n/gl.po
odoo_addons/mrp_bom_location/i18n/hr.po
odoo_addons/mrp_bom_location/i18n/hr_HR.po
odoo_addons/mrp_bom_location/i18n/it.po
odoo_addons/mrp_bom_location/i18n/mrp_bom_location.pot
odoo_addons/mrp_bom_location/i18n/nl.po
odoo_addons/mrp_bom_location/i18n/nl_NL.po
odoo_addons/mrp_bom_location/i18n/pt.po
odoo_addons/mrp_bom_location/i18n/pt_BR.po
odoo_addons/mrp_bom_location/i18n/pt_PT.po
odoo_addons/mrp_bom_location/i18n/ro.po
odoo_addons/mrp_bom_location/i18n/sl.po
odoo_addons/mrp_bom_location/i18n/tr.po
odoo_addons/mrp_bom_location/i18n/tr_TR.po
odoo_addons/mrp_bom_location/i18n/vi_VN.po
odoo_addons/mrp_bom_location/i18n/zh_CN.po
odoo_addons/mrp_bom_location/models/__init__.py
odoo_addons/mrp_bom_location/models/mrp_bom.py
odoo_addons/mrp_bom_location/report/__init__.py
odoo_addons/mrp_bom_location/report/bom_structure.py
odoo_addons/mrp_bom_location/static/description/icon.png
odoo_addons/mrp_bom_location/views/mrp_view.xml
odoo_addons/mrp_bom_location/views/report_mrpbomstructure.xml
odoo9_addon_mrp_bom_location-9.0.1.0.0.99.dev6.dist-info/METADATA
odoo9_addon_mrp_bom_location-9.0.1.0.0.99.dev6.dist-info/WHEEL
odoo9_addon_mrp_bom_location-9.0.1.0.0.99.dev6.dist-info/namespace_packages.txt
odoo9_addon_mrp_bom_location-9.0.1.0.0.99.dev6.dist-info/top_level.txt
odoo9_addon_mrp_bom_location-9.0.1.0.0.99.dev6.dist-info/RECORD
